{
  "fatos_relevantes": [
    {
      "data": "1989-10-15",
      "titulo": "teste",
      "textorelevante": "teste222222222222222222222222",
      "paciente": "8952",
      "id": 1
    },
    {
      "data": "2021-10-12",
      "titulo": "teste",
      "textorelevante": "teste2",
      "paciente": "1014",
      "id": 2
    }
  ],
  "sessao": [
    {
      "data": "1989-10-15",
      "hora_Inicio": "15:10",
      "hora_Fim": "16:10",
      "titulo_sessao": "teste2222",
      "resumo_sessao": "teste222",
      "valor_sessao": "99",
      "forma_sessao": "Pix",
      "status": "pago",
      "paciente": "8952",
      "id": 1
    },
    {
      "data": "2023-10-15",
      "hora_Inicio": "15:00",
      "hora_Fim": "06:00",
      "titulo_sessao": "sessao nova",
      "resumo_sessao": "teste",
      "valor_sessao": "99",
      "forma_sessao": "Pix",
      "status": "pago",
      "paciente": "8952",
      "id": 2
    },
    {
      "data": "1989-10-15",
      "hora_Inicio": "15:10",
      "hora_Fim": "16:10",
      "titulo_sessao": "sessao nova",
      "resumo_sessao": "teste",
      "valor_sessao": "99",
      "forma_sessao": "Pix",
      "status": "pago",
      "paciente": "1385",
      "id": 3
    },
    {
      "data": "2000-10-15",
      "hora_Inicio": "15:00",
      "hora_Fim": "16:00",
      "titulo_sessao": "sessao nova",
      "resumo_sessao": "teste",
      "valor_sessao": "99",
      "forma_sessao": "Pix",
      "status": "pago",
      "paciente": "1014",
      "id": 4
    },
    {
      "data": "2023-10-15",
      "hora_Inicio": "15:10",
      "hora_Fim": "16:10",
      "titulo_sessao": "sessao nova",
      "resumo_sessao": "teste",
      "valor_sessao": "99",
      "forma_sessao": "Pix",
      "status": "pago",
      "paciente": "1014",
      "id": 5
    }
  ],
  "Paciente": [
    {
      "id": 1014,
      "cpf": "08670087685",
      "nome": "arthur nicolas",
      "dnascimento": "1989-10-12",
      "email": "xxmarcio.henrique@gmail.com",
      "sexo": "Masculino",
      "nacionalidade": "brasileira",
      "naturalidade": "serro",
      "profissao": "operador de maquina",
      "escolaridade": "Fundamental",
      "estado_civil": "Solteiro(a)",
      "mae": "maria",
      "pai": "geraldo"
    },
    {
      "id": 3669,
      "cpf": "12802103628",
      "nome": "marcio",
      "dnascimento": "1990-10-12",
      "email": "xxmarcio.henrique@gmail.com",
      "sexo": "Masculino",
      "nacionalidade": "brasileira",
      "naturalidade": "serro",
      "profissao": "operador de maquina",
      "escolaridade": "Fundamental",
      "estado_civil": "Solteiro(a)",
      "mae": "maria",
      "pai": "geraldo"
    }
  ],
  "login": [
    {
      "nome": "marcio",
      "mail": "xxmarcio.henrique@gmail.com",
      "senha1": "atletico12",
      "confirmarsenha": "atletico12",
      "id": 1
    },
    {
      "nome": "esdras",
      "mail": "kellyalves@gmail.com",
      "senha1": "1234",
      "confirmarsenha": "1234",
      "id": 2
    },
    {
      "nome": "xxx",
      "mail": "kellyalves@gmail.com",
      "senha1": "1234",
      "confirmarsenha": "1234",
      "id": 3
    },
    {
      "nome": "marciohenrique",
      "mail": "xxmarcio.henrique@gmail.com",
      "senha1": "1234",
      "confirmarsenha": "1234",
      "id": 4
    },
    {
      "nome": "kelly",
      "mail": "kellyalves@gmail.com",
      "senha1": "1234",
      "confirmarsenha": "1234",
      "id": 5
    },
    {
      "nome": "kelly",
      "mail": "kellyalves@gmail.com",
      "senha1": "1234",
      "confirmarsenha": "1234",
      "id": 6
    },
    {
      "nome": "",
      "mail": "",
      "senha1": "",
      "confirmarsenha": "",
      "id": 7
    },
    {
      "nome": "",
      "mail": "",
      "senha1": "",
      "confirmarsenha": "",
      "id": 8
    },
    {
      "nome": "marciohenrique",
      "mail": "xxmarcio.henrique@gmail.com",
      "senha1": "atletico12",
      "confirmarsenha": "atletico12",
      "id": 9
    },
    {
      "nome": "kelly",
      "mail": "kellyalves@gmail.com",
      "senha1": "atletico12",
      "confirmarsenha": "atletico12",
      "id": 10
    },
    {
      "nome": "marcio",
      "mail": "xxmarcio.henrique@gmail.com",
      "senha1": "atletico",
      "confirmarsenha": "atletico",
      "id": 11
    },
    {
      "nome": "marcio",
      "mail": "xxmarcio.henrique@gmail.com",
      "senha1": "Atletic@12",
      "confirmarsenha": "Atletic@12",
      "id": 12
    }
  ],
  "comments": [
    {
      "id": 1,
      "body": "some comment",
      "postId": 1
    }
  ],
  "profile": {
    "name": "typicode"
  }
}